{
  "project_info": {
    "project_number": "222833132940",
    "firebase_url": "https://metro-app-3e121-default-rtdb.firebaseio.com",
    "project_id": "metro-app-3e121",
    "storage_bucket": "metro-app-3e121.firebasestorage.app"
  },
  "client": [
    {
      "client_info": {
        "mobilesdk_app_id": "1:222833132940:android:2e585cbb72e858e55782a9",
        "android_client_info": {
          "package_name": "com.example.metro_app"
        }
      },
      "oauth_client": [
        {
          "client_id": "222833132940-7a4socoefr7c17v61ue6rd1k0p56eriq.apps.googleusercontent.com",
          "client_type": 1,
          "android_info": {
            "package_name": "com.example.metro_app",
            "certificate_hash": "06d97a8875e6dca20d8f03ca9fc592ed3e8d8e1f"
          }
        },
        {
          "client_id": "222833132940-2ahj96m2p17qnkajjpmhr86onjliit3v.apps.googleusercontent.com",
          "client_type": 3
        }
      ],
      "api_key": [
        {
          "current_key": "AIzaSyD2qdsVHd49RQE15ya3rq7cmHGNmAyZbJk"
        }
      ],
      "services": {
        "appinvite_service": {
          "other_platform_oauth_client": [
            {
              "client_id": "222833132940-2ahj96m2p17qnkajjpmhr86onjliit3v.apps.googleusercontent.com",
              "client_type": 3
            }
          ]
        }
      }
    }
  ],
  "configuration_version": "1"
}